duckreg/__init__.py
duckreg/demean.py
duckreg/duckreg.py
duckreg/estimators.py
duckreg-0.2.dist-info/licenses/LICENSE
tests/__init__.py
tests/conftest.py
tests/test_fitter.py
tests/utils.py
duckreg-0.2.dist-info/METADATA
duckreg-0.2.dist-info/WHEEL
duckreg-0.2.dist-info/top_level.txt
duckreg-0.2.dist-info/RECORD
