Metadata-Version: 2.4
Name: duckreg
Version: 0.2
Summary: A package for Regression in compressed representation powered by DuckDB
Home-page: https://github.com/apoorvalal/duckreg
Author: Apoorva Lal
Author-email: lal.apoorva@gmail.com
License: MIT
Keywords: statistics,econometrics,sufficient statistics,bootstrap
Classifier: Development Status :: 3 - Alpha
Classifier: Intended Audience :: Developers
Classifier: License :: OSI Approved :: MIT License
Classifier: Programming Language :: Python :: 3.9
Classifier: Programming Language :: Python :: 3.10
Classifier: Programming Language :: Python :: 3.11
Classifier: Programming Language :: Python :: 3.12
Requires-Python: >=3.7
License-File: LICENSE
Dynamic: author
Dynamic: author-email
Dynamic: classifier
Dynamic: description
Dynamic: description-content-type
Dynamic: home-page
Dynamic: keywords
Dynamic: license
Dynamic: license-file
Dynamic: requires-python
Dynamic: summary
